salamander/__init__.py
salamander/consts.py
salamander/initialization/__init__.py
salamander/initialization/initialize.py
salamander/initialization/methods.py
salamander/models/__init__.py
salamander/models/_utils_corrnmf.py
salamander/models/_utils_klnmf.py
salamander/models/corrnmf.py
salamander/models/corrnmf_det.py
salamander/models/klnmf.py
salamander/models/mmcorrnmf.py
salamander/models/mvnmf.py
salamander/models/signature_nmf.py
salamander/models/standard_nmf.py
salamander/plot.py
salamander/tools.py
salamander/utils.py
salamander_learn-0.4.2.dist-info/LICENSE
salamander_learn-0.4.2.dist-info/METADATA
salamander_learn-0.4.2.dist-info/WHEEL
salamander_learn-0.4.2.dist-info/RECORD
