Metadata-Version: 2.1
Name: salamander-learn
Version: 0.4.2
Summary: Salamander is a non-negative matrix factorization framework for signature analysis
License: MIT
Author: Benedikt Geiger
Maintainer: Benedikt Geiger
Maintainer-email: benedikt_geiger@hms.harvard.edu
Requires-Python: >=3.9,<3.12
Classifier: License :: OSI Approved :: MIT License
Classifier: Programming Language :: Python :: 3
Classifier: Programming Language :: Python :: 3.9
Classifier: Programming Language :: Python :: 3.10
Classifier: Programming Language :: Python :: 3.11
Requires-Dist: adjustText (>=0.8,<0.9)
Requires-Dist: anndata (>=0.10.5,<0.10.9)
Requires-Dist: fastcluster (>=1.2.6,<2.0.0)
Requires-Dist: matplotlib (>=3.7.1,<4.0.0)
Requires-Dist: mudata (>=0.2.3,<0.3.0)
Requires-Dist: numba (>=0.59,<0.60)
Requires-Dist: numpy (>=1.24.3,<2.0.0)
Requires-Dist: pandas (>=1.5.3,<2.0.0)
Requires-Dist: scikit-learn (>=1.3.0,<2.0.0)
Requires-Dist: scipy (>=1.10.1,<2.0.0)
Requires-Dist: seaborn (>=0.13.0,<0.14.0)
Requires-Dist: umap-learn (>=0.5.4,<0.6.0)
